hdtgraph/DoublyLinkedList.py
hdtgraph/DynamicGraph.py
hdtgraph/ETTree.py
hdtgraph/Tree.py
hdtgraph/__init__.py
hdtgraph-0.0.1.dist-info/LICENSE
hdtgraph-0.0.1.dist-info/METADATA
hdtgraph-0.0.1.dist-info/WHEEL
hdtgraph-0.0.1.dist-info/top_level.txt
hdtgraph-0.0.1.dist-info/RECORD
