Metadata-Version: 2.1
Name: hdtgraph
Version: 0.0.1
Summary: Implementation of the dynamic graph data structure described by Holm, de Lichtenberg and Thorup in 2001 (HDT algorithm).
Home-page: https://github.com/david-schaller/hdt-graph
Author: David Schaller
Author-email: david@0x002A.com
License: UNKNOWN
Platform: UNKNOWN
Classifier: Programming Language :: Python :: 3
Classifier: License :: OSI Approved :: MIT License
Classifier: Operating System :: OS Independent
